craft_ls/__init__.py
craft_ls/__main__.py
craft_ls/cli.py
craft_ls/core.py
craft_ls/server.py
craft_ls/settings.py
craft_ls/types_.py
craft_ls/schemas/charmcraft.json
craft_ls/schemas/rockcraft.json
craft_ls/schemas/snapcraft.json
craft_ls-0.4.1.dist-info/METADATA
craft_ls-0.4.1.dist-info/WHEEL
craft_ls-0.4.1.dist-info/entry_points.txt
craft_ls-0.4.1.dist-info/licenses/LICENSE
craft_ls-0.4.1.dist-info/RECORD
