Metadata-Version: 2.4
Name: craft-ls
Version: 0.4.1
Summary: A Language Server Protocol implementation for *craft files.
Project-URL: Repository, https://github.com/batalex/craft-ls
Project-URL: Releases, https://github.com/batalex/craft-ls/releases
Author-email: Alex Batisse <alex.batisse@canonical.com>
License-Expression: BSD-3-Clause
License-File: LICENSE
Keywords: charmcraft,lsp,rockcraft,snapcraft
Classifier: Development Status :: 3 - Alpha
Classifier: Intended Audience :: Developers
Classifier: License :: OSI Approved :: BSD License
Classifier: Operating System :: OS Independent
Classifier: Programming Language :: Python
Classifier: Programming Language :: Python :: 3 :: Only
Classifier: Programming Language :: Python :: 3.12
Requires-Python: >=3.12
Requires-Dist: jsonpath-ng>=1.7.0
Requires-Dist: jsonref>=1.1.0
Requires-Dist: jsonschema>=4.23.0
Requires-Dist: lsprotocol>=2025.0.0
Requires-Dist: more-itertools>=10.7.0
Requires-Dist: pygls>=1.1.0
Requires-Dist: pyyaml>=6.0.2
Requires-Dist: referencing>=0.36.2
